setup.cfg
setup.py
invo/__init__.py
invo.egg-info/PKG-INFO
invo.egg-info/SOURCES.txt
invo.egg-info/dependency_links.txt
invo.egg-info/not-zip-safe
invo.egg-info/requires.txt
invo.egg-info/top_level.txt
invo/LinearModels/AbsoluteDualityGap.py
invo/LinearModels/RelativeDualityGap.py
invo/LinearModels/__init__.py
invo/LinearModels/pNorm.py
invo/utils/__init__.py
invo/utils/fwdutils.py
invo/utils/invoutils.py