Metadata-Version: 1.1
Name: invo
Version: 0.3
Summary: A Generalized Inverse Optimization package.
Home-page: https://github.com/rafidrm/invo
Author: Rafid Mahmood
Author-email: rafid.mahmood@mail.utoronto.ca
License: MIT
Download-URL: https://github.com/rafidrm/invo/archive/0.3.tar.gz
Keywords: optimization,inverse
Platform: UNKNOWN
